LICENSE
shajango/__init__.py
shajango/py.typed
shajango/shajango.py
shajango-0.0.1.dist-info/LICENSE
shajango-0.0.1.dist-info/WHEEL
shajango-0.0.1.dist-info/METADATA
shajango-0.0.1.dist-info/RECORD
