Metadata-Version: 2.1
Name: shajango
Version: 0.0.1
Summary: 一个基于Django的CMS。
Home-page: https://github.com/llango/shajango
License: MIT
Author: rontom ai
Author-email: rontomai@gmail.com
Requires-Python: >=3.7,<4.0
Classifier: License :: OSI Approved :: MIT License
Classifier: Natural Language :: English
Classifier: Programming Language :: Python :: 3
Classifier: Programming Language :: Python :: 3.7
Classifier: Programming Language :: Python :: 3.8
Classifier: Programming Language :: Python :: 3.9
Requires-Dist: importlib_metadata (>=3.4.0,<4.0.0)
